MANIFEST.in
Makefile
README
YOLOLogic-2.1.3.html
setup.py
Examples/README
Examples/multi_instance_object_detection.py
Examples/single_instance_object_detection.py
ExamplesRegionProposals/README
ExamplesRegionProposals/interactive_graph_based_segmentation.py
ExamplesRegionProposals/selective_search.py
ExamplesRegionProposals/torchvision_based_image_processing.py
ExamplesRegionProposals/torchvision_some_basic_transformations.py
ExamplesRegionProposals/color_blobs/color_blobs.jpg
ExamplesRegionProposals/color_blobs/selective_search.py
ExamplesRegionProposals/images/disk.jpg
ExamplesRegionProposals/images/london6.jpg
ExamplesRegionProposals/images/mondrian.jpg
ExamplesRegionProposals/images/polkadots.jpg
ExamplesRegionProposals/images/rect_with_4_colors.jpg
ExamplesRegionProposals/images/tulip0036.jpg
ExamplesRegionProposals/images/wallpic2.jpg
ExamplesRegionProposals/mondrian/README
ExamplesRegionProposals/mondrian/mondrian.jpg
ExamplesRegionProposals/mondrian/selective_search.py
ExamplesRegionProposals/wallpic2/selective_search.py
ExamplesRegionProposals/wallpic2/wallpic2.jpg
TestYOLOLogic/Test.py
TestYOLOLogic/TestImageConversion.py
TestYOLOLogic/TestImageLoadingAndDataExtraction.py
TestYOLOLogic/YOLOLogic.py
TestYOLOLogic/halfsun.jpg
YOLOLogic/YOLOLogic.py
YOLOLogic/__init__.py
YOLOLogic.egg-info/PKG-INFO
YOLOLogic.egg-info/SOURCES.txt
YOLOLogic.egg-info/dependency_links.txt
YOLOLogic.egg-info/top_level.txt