Metadata-Version: 2.1
Name: YOLOLogic
Version: 2.1.3
Summary: An educational module for experimenting with the YOLO logic for multi-instance object detection and for generating region proposals with graph-based algorithms
Home-page: https://engineering.purdue.edu/kak/distYOLO/YOLOLogic-2.1.3.html
Author: Avinash Kak
Author-email: kak@purdue.edu
Maintainer: Avinash Kak
Maintainer-email: kak@purdue.edu
License: Python Software Foundation License
Download-URL: https://engineering.purdue.edu/kak/distYOLO/YOLOLogic-2.1.3.tar.gz
Keywords: object detection,image segmentation,computer vision
Platform: All platforms
Classifier: Topic :: Scientific/Engineering :: Image Recognition
Classifier: Programming Language :: Python :: 3.10
